cocube/__about__.py
cocube/__init__.py
cocube-0.0.4.dist-info/METADATA
cocube-0.0.4.dist-info/WHEEL
cocube-0.0.4.dist-info/licenses/LICENSE.txt
cocube-0.0.4.dist-info/RECORD
