Metadata-Version: 2.3
Name: cocube
Version: 0.0.4
Project-URL: Documentation, https://github.com/wwj718/cocube#readme
Project-URL: Issues, https://github.com/wwj718/cocube/issues
Project-URL: Source, https://github.com/wwj718/cocube
Author-email: wwj718 <wuwenjie718@gmail.com>
License-Expression: MIT
License-File: LICENSE.txt
Classifier: Development Status :: 4 - Beta
Classifier: Programming Language :: Python
Classifier: Programming Language :: Python :: 3.8
Classifier: Programming Language :: Python :: 3.9
Classifier: Programming Language :: Python :: 3.10
Classifier: Programming Language :: Python :: 3.11
Classifier: Programming Language :: Python :: 3.12
Classifier: Programming Language :: Python :: Implementation :: CPython
Classifier: Programming Language :: Python :: Implementation :: PyPy
Requires-Python: >=3.8
Requires-Dist: microblocks==0.9.1
